cpbd/__init__.py
cpbd/compute.py
cpbd/octave.py
cpbd_py312-1.0.3.dist-info/licenses/LICENSE.txt
cpbd_py312-1.0.3.dist-info/METADATA
cpbd_py312-1.0.3.dist-info/WHEEL
cpbd_py312-1.0.3.dist-info/top_level.txt
cpbd_py312-1.0.3.dist-info/RECORD
