Metadata-Version: 2.4
Name: cpbd-py312
Version: 1.0.3
Summary: Calculate the sharpness of an image with the CPBD metric (Python 3.12+ compatible)
Author-email: nawta <nawta@g.ecc.u-tokyo.ac.jp>
License: Proprietary
Project-URL: Homepage, https://github.com/nawta/python-cpbd-py312
Keywords: sharpness,metric,blur,cumulative probability,no-reference,objective,perceptual
Classifier: Development Status :: 5 - Production/Stable
Classifier: Intended Audience :: Science/Research
Classifier: Topic :: Scientific/Engineering
Classifier: License :: Other/Proprietary License
Classifier: Programming Language :: Python :: 3
Classifier: Programming Language :: Python :: 3.12
Requires-Python: >=3.8
License-File: LICENSE.txt
Requires-Dist: matplotlib>=3.5.0
Requires-Dist: numpy>=1.21.0
Requires-Dist: scikit-image>=0.19.0
Requires-Dist: scipy>=1.7.0
Requires-Dist: imageio>=2.9.0
Provides-Extra: dev
Requires-Dist: pandas>=1.3.0; extra == "dev"
Requires-Dist: pytest>=6.0.0; extra == "dev"
Requires-Dist: scikit-learn>=1.0.0; extra == "dev"
Requires-Dist: tox>=3.24.0; extra == "dev"
Dynamic: license-file
